{
	"name": "AzureSqlTable1",
	"properties": {
		"linkedServiceName": {
			"referenceName": "AzureSqlDatabase1",
			"type": "LinkedServiceReference"
		},
		"annotations": [],
		"type": "AzureSqlTable",
		"schema": [
			{
				"name": "files_id",
				"type": "int",
				"precision": 10
			},
			{
				"name": "files_name",
				"type": "varchar"
			},
			{
				"name": "src_path",
				"type": "varchar"
			},
			{
				"name": "tar_path",
				"type": "varchar"
			}
		],
		"typeProperties": {
			"schema": "dbo",
			"table": "filesinfo"
		}
	},
	"type": "Microsoft.DataFactory/factories/datasets"
}